syslog2/__init__.py
syslog2/_syslog2.py
syslog2/_utils.py
syslog2/_version.py
syslog2-0.5.0.dist-info/LICENSE
syslog2-0.5.0.dist-info/METADATA
syslog2-0.5.0.dist-info/WHEEL
syslog2-0.5.0.dist-info/top_level.txt
syslog2-0.5.0.dist-info/zip-safe
syslog2-0.5.0.dist-info/RECORD
