Metadata-Version: 2.1
Name: syslog2
Version: 0.5.0
Summary: An improved SysLogHandler for Python
Home-page: https://github.com/andy-maier/syslog2
Author: Andreas Maier
Author-email: andreas.r.maier@gmx.de
Maintainer: Andreas Maier
Maintainer-email: andreas.r.maier@gmx.de
License: Apache Software License 2.0
Project-URL: Bug Tracker, https://github.com/andy-maier/syslog2/issues
Project-URL: Documentation, https://syslog2.readthedocs.io/en/latest/
Project-URL: Source Code, https://github.com/andy-maier/syslog2
Platform: any
Classifier: Development Status :: 4 - Beta
Classifier: Intended Audience :: Developers
Classifier: License :: OSI Approved :: Apache Software License
Classifier: Operating System :: OS Independent
Classifier: Programming Language :: Python :: 2
Classifier: Programming Language :: Python :: 2.7
Classifier: Programming Language :: Python :: 3
Classifier: Programming Language :: Python :: 3.4
Classifier: Programming Language :: Python :: 3.5
Classifier: Programming Language :: Python :: 3.6
Classifier: Programming Language :: Python :: 3.7
Classifier: Programming Language :: Python :: 3.8
Classifier: Programming Language :: Python :: 3.9
Classifier: Programming Language :: Python :: 3.10
Classifier: Topic :: Software Development :: Libraries :: Python Modules
Requires-Python: >=2.7, !=3.0.*, !=3.1.*, !=3.2.*, !=3.3.*
License-File: LICENSE
Requires-Dist: six (>=1.14.0)
Requires-Dist: pytz (>=2019.1)
Requires-Dist: macos-oslog (>=0.5.0) ; sys_platform == "darwin" and python_version >= "3.5"
Requires-Dist: pywin32 (>=228) ; sys_platform == "win32" and python_version <= "3.9"
Requires-Dist: pywin32 (>=302) ; sys_platform == "win32" and python_version >= "3.10"
Provides-Extra: test
Requires-Dist: packaging (>=17.0) ; extra == 'test'
Requires-Dist: pluggy (>=0.13.1) ; extra == 'test'
Requires-Dist: pathlib2 (<3,>=2.3.3) ; (python_version < "3.4" and sys_platform != "win32") and extra == 'test'
Requires-Dist: pytest (<5.0.0,>=4.3.1) ; (python_version < "3.5") and extra == 'test'
Requires-Dist: virtualenv (!=20.0.19,!=20.0.32,>=16.1.0) ; (python_version <= "3.4") and extra == 'test'
Requires-Dist: pytest (>=6.2.5) ; (python_version >= "3.10") and extra == 'test'
Requires-Dist: virtualenv (>=20.1.0) ; (python_version >= "3.5") and extra == 'test'
Requires-Dist: pytest (!=6.0,>=4.3.1) ; (python_version >= "3.5" and python_version <= "3.6") and extra == 'test'
Requires-Dist: pytest (!=6.0,>=4.4.0) ; (python_version >= "3.7" and python_version <= "3.9") and extra == 'test'
